openapi_transmog/__main__.py
openapi_transmog/api_call.py
openapi_transmog/schema.py
openapi_transmog-0.1.0.dist-info/LICENSE
openapi_transmog-0.1.0.dist-info/METADATA
openapi_transmog-0.1.0.dist-info/WHEEL
openapi_transmog-0.1.0.dist-info/RECORD
