Metadata-Version: 2.3
Name: openapi-transmog
Version: 0.1.0
Summary: Simple OpenAPI transmogrifier that produces Python code
License: MIT
Author: Mia yun Ruse
Author-email: mia@yunru.se
Requires-Python: >=3.8
Classifier: License :: OSI Approved :: MIT License
Classifier: Programming Language :: Python :: 3
Classifier: Programming Language :: Python :: 3.8
Classifier: Programming Language :: Python :: 3.9
Classifier: Programming Language :: Python :: 3.10
Classifier: Programming Language :: Python :: 3.11
Classifier: Programming Language :: Python :: 3.12
Classifier: Programming Language :: Python :: 3.13
